graphql_introspection/GraphQL.py
graphql_introspection/__init__.py
graphql_introspection/src/display.py
graphql_introspection/src/parser.py
graphql_introspection/src/request.py
graphql_introspection/src/utils.py
graphql_introspection-0.1.0.dist-info/METADATA
graphql_introspection-0.1.0.dist-info/WHEEL
graphql_introspection-0.1.0.dist-info/licenses/LICENSE
graphql_introspection-0.1.0.dist-info/RECORD
