Metadata-Version: 2.1
Name: graphql_introspection
Version: 0.1.0
Summary: Classic GraphQL Introspection
Project-URL: Homepage, https://github.com/antonin-alves/GraphQL-Instrospection
Project-URL: Bug Tracker, https://github.com/antonin-alves/GraphQL-Instrospection/issues
Author-email: Antonin Alves <antonin@alors-la.center>
License: C'est cadeau
License-File: LICENSE
Classifier: License :: OSI Approved :: MIT License
Classifier: Operating System :: OS Independent
Classifier: Programming Language :: Python :: 3
Requires-Python: >=3.7
